<annotation>
	<folder>Unknown</folder>
	<filename>1815.jpg</filename>
	<path>Unknown</path>
	<source>
		<database>MAR20</database>
	</source>
	<size>
		<width>800</width>
		<height>800</height>
		<depth>3</depth>
	</size>
	<segmented>0</segmented>
	<object>
		<name>A5</name>
		<pose>Unspecified</pose>
		<truncated>0</truncated>
		<difficult>0</difficult>
		<bndbox>
			<xmin>228</xmin>
			<ymin>50</ymin>
			<xmax>344</xmax>
			<ymax>208</ymax>
		</bndbox>
	</object>
	<object>
		<name>A5</name>
		<pose>Unspecified</pose>
		<truncated>0</truncated>
		<difficult>0</difficult>
		<bndbox>
			<xmin>353</xmin>
			<ymin>73</ymin>
			<xmax>461</xmax>
			<ymax>227</ymax>
		</bndbox>
	</object>
	<object>
		<name>A5</name>
		<pose>Unspecified</pose>
		<truncated>0</truncated>
		<difficult>0</difficult>
		<bndbox>
			<xmin>478</xmin>
			<ymin>84</ymin>
			<xmax>590</xmax>
			<ymax>243</ymax>
		</bndbox>
	</object>
	<object>
		<name>A5</name>
		<pose>Unspecified</pose>
		<truncated>0</truncated>
		<difficult>0</difficult>
		<bndbox>
			<xmin>154</xmin>
			<ymin>621</ymin>
			<xmax>267</xmax>
			<ymax>772</ymax>
		</bndbox>
	</object>
</annotation>