<annotation>
	<filename>270.xml</filename>
	<source>
		<database>MAR20</database>
	</source>
	<size>
		<width>807</width>
		<height>886</height>
		<depth>3</depth>
	</size>
	<segmented>0</segmented>
	<object>
		<name>A8</name>
		<bndbox>
			<xmin>183</xmin>
			<ymin>13</ymin>
			<xmax>334</xmax>
			<ymax>167</ymax>
		</bndbox>
	<difficult>0</difficult></object>
	<object>
		<name>A8</name>
		<bndbox>
			<xmin>265</xmin>
			<ymin>250</ymin>
			<xmax>407</xmax>
			<ymax>406</ymax>
		</bndbox>
	<difficult>0</difficult></object>
	<object>
		<name>A8</name>
		<bndbox>
			<xmin>347</xmin>
			<ymin>477</ymin>
			<xmax>483</xmax>
			<ymax>639</ymax>
		</bndbox>
	<difficult>0</difficult></object>
	<object>
		<name>A8</name>
		<bndbox>
			<xmin>416</xmin>
			<ymin>713</ymin>
			<xmax>561</xmax>
			<ymax>871</ymax>
		</bndbox>
	<difficult>0</difficult></object>
</annotation>