<annotation>
	<folder>Unknown</folder>
	<filename>2158.jpg</filename>
	<path>Unknown</path>
	<source>
		<database>MAR20</database>
	</source>
	<size>
		<width>800</width>
		<height>800</height>
		<depth>3</depth>
	</size>
	<segmented>0</segmented>
	<object>
		<name>A17</name>
		<pose>Unspecified</pose>
		<truncated>0</truncated>
		<difficult>0</difficult>
		<bndbox>
			<xmin>142</xmin>
			<ymin>189</ymin>
			<xmax>267</xmax>
			<ymax>308</ymax>
		</bndbox>
	</object>
	<object>
		<name>A17</name>
		<pose>Unspecified</pose>
		<truncated>0</truncated>
		<difficult>0</difficult>
		<bndbox>
			<xmin>185</xmin>
			<ymin>319</ymin>
			<xmax>314</xmax>
			<ymax>441</ymax>
		</bndbox>
	</object>
	<object>
		<name>A17</name>
		<pose>Unspecified</pose>
		<truncated>0</truncated>
		<difficult>0</difficult>
		<bndbox>
			<xmin>246</xmin>
			<ymin>490</ymin>
			<xmax>381</xmax>
			<ymax>627</ymax>
		</bndbox>
	</object>
</annotation>