<annotation>
	<folder>Unknown</folder>
	<filename>2879.jpg</filename>
	<path>Unknown</path>
	<source>
		<database>MAR20</database>
	</source>
	<size>
		<width>800</width>
		<height>800</height>
		<depth>3</depth>
	</size>
	<segmented>0</segmented>
	<object>
		<name>A4</name>
		<pose>Unspecified</pose>
		<truncated>0</truncated>
		<difficult>0</difficult>
		<bndbox>
			<xmin>471</xmin>
			<ymin>292</ymin>
			<xmax>640</xmax>
			<ymax>440</ymax>
		</bndbox>
	</object>
	<object>
		<name>A4</name>
		<pose>Unspecified</pose>
		<truncated>0</truncated>
		<difficult>0</difficult>
		<bndbox>
			<xmin>461</xmin>
			<ymin>620</ymin>
			<xmax>614</xmax>
			<ymax>782</ymax>
		</bndbox>
	</object>
	<object>
		<name>A4</name>
		<pose>Unspecified</pose>
		<truncated>0</truncated>
		<difficult>0</difficult>
		<bndbox>
			<xmin>310</xmin>
			<ymin>616</ymin>
			<xmax>460</xmax>
			<ymax>779</ymax>
		</bndbox>
	</object>
	<object>
		<name>A4</name>
		<pose>Unspecified</pose>
		<truncated>0</truncated>
		<difficult>0</difficult>
		<bndbox>
			<xmin>165</xmin>
			<ymin>607</ymin>
			<xmax>313</xmax>
			<ymax>774</ymax>
		</bndbox>
	</object>
	<object>
		<name>A14</name>
		<pose>Unspecified</pose>
		<truncated>0</truncated>
		<difficult>0</difficult>
		<bndbox>
			<xmin>490</xmin>
			<ymin>34</ymin>
			<xmax>593</xmax>
			<ymax>124</ymax>
		</bndbox>
	</object>
</annotation>