<annotation>
	<folder>Unknown</folder>
	<filename>3003.jpg</filename>
	<path>Unknown</path>
	<source>
		<database>MAR20</database>
	</source>
	<size>
		<width>800</width>
		<height>800</height>
		<depth>3</depth>
	</size>
	<segmented>0</segmented>
	<object>
		<name>A15</name>
		<pose>Unspecified</pose>
		<truncated>0</truncated>
		<difficult>0</difficult>
		<bndbox>
			<xmin>441</xmin>
			<ymin>82</ymin>
			<xmax>555</xmax>
			<ymax>184</ymax>
		</bndbox>
	</object>
	<object>
		<name>A15</name>
		<pose>Unspecified</pose>
		<truncated>0</truncated>
		<difficult>0</difficult>
		<bndbox>
			<xmin>376</xmin>
			<ymin>182</ymin>
			<xmax>492</xmax>
			<ymax>285</ymax>
		</bndbox>
	</object>
	<object>
		<name>A15</name>
		<pose>Unspecified</pose>
		<truncated>0</truncated>
		<difficult>0</difficult>
		<bndbox>
			<xmin>269</xmin>
			<ymin>268</ymin>
			<xmax>390</xmax>
			<ymax>369</ymax>
		</bndbox>
	</object>
	<object>
		<name>A15</name>
		<pose>Unspecified</pose>
		<truncated>0</truncated>
		<difficult>0</difficult>
		<bndbox>
			<xmin>212</xmin>
			<ymin>378</ymin>
			<xmax>332</xmax>
			<ymax>478</ymax>
		</bndbox>
	</object>
	<object>
		<name>A15</name>
		<pose>Unspecified</pose>
		<truncated>0</truncated>
		<difficult>0</difficult>
		<bndbox>
			<xmin>129</xmin>
			<ymin>472</ymin>
			<xmax>246</xmax>
			<ymax>574</ymax>
		</bndbox>
	</object>
	<object>
		<name>A15</name>
		<pose>Unspecified</pose>
		<truncated>0</truncated>
		<difficult>0</difficult>
		<bndbox>
			<xmin>68</xmin>
			<ymin>578</ymin>
			<xmax>188</xmax>
			<ymax>682</ymax>
		</bndbox>
	</object>
</annotation>