<annotation>
	<folder>Unknown</folder>
	<filename>625.jpg</filename>
	<path>Unknown</path>
	<source>
		<database>MAR20</database>
	</source>
	<size>
		<width>875</width>
		<height>823</height>
		<depth>3</depth>
	</size>
	<segmented>0</segmented>
	<object>
		<name>A11</name>
		<pose>Unspecified</pose>
		<truncated>0</truncated>
		<difficult>0</difficult>
		<bndbox>
			<xmin>165</xmin>
			<ymin>39</ymin>
			<xmax>259</xmax>
			<ymax>123</ymax>
		</bndbox>
	</object>
	<object>
		<name>A11</name>
		<pose>Unspecified</pose>
		<truncated>0</truncated>
		<difficult>0</difficult>
		<bndbox>
			<xmin>344</xmin>
			<ymin>192</ymin>
			<xmax>436</xmax>
			<ymax>284</ymax>
		</bndbox>
	</object>
	<object>
		<name>A11</name>
		<pose>Unspecified</pose>
		<truncated>0</truncated>
		<difficult>0</difficult>
		<bndbox>
			<xmin>520</xmin>
			<ymin>358</ymin>
			<xmax>613</xmax>
			<ymax>451</ymax>
		</bndbox>
	</object>
	<object>
		<name>A11</name>
		<pose>Unspecified</pose>
		<truncated>0</truncated>
		<difficult>0</difficult>
		<bndbox>
			<xmin>267</xmin>
			<ymin>509</ymin>
			<xmax>355</xmax>
			<ymax>601</ymax>
		</bndbox>
	</object>
	<object>
		<name>A11</name>
		<pose>Unspecified</pose>
		<truncated>0</truncated>
		<difficult>0</difficult>
		<bndbox>
			<xmin>66</xmin>
			<ymin>337</ymin>
			<xmax>160</xmax>
			<ymax>426</ymax>
		</bndbox>
	</object>
	<object>
		<name>A11</name>
		<pose>Unspecified</pose>
		<truncated>0</truncated>
		<difficult>0</difficult>
		<bndbox>
			<xmin>169</xmin>
			<ymin>420</ymin>
			<xmax>264</xmax>
			<ymax>511</ymax>
		</bndbox>
	</object>
	<object>
		<name>A11</name>
		<pose>Unspecified</pose>
		<truncated>0</truncated>
		<difficult>0</difficult>
		<bndbox>
			<xmin>708</xmin>
			<ymin>493</ymin>
			<xmax>814</xmax>
			<ymax>618</ymax>
		</bndbox>
	</object>
	<object>
		<name>A11</name>
		<pose>Unspecified</pose>
		<truncated>0</truncated>
		<difficult>0</difficult>
		<bndbox>
			<xmin>339</xmin>
			<ymin>597</ymin>
			<xmax>464</xmax>
			<ymax>715</ymax>
		</bndbox>
	</object>
	<object>
		<name>A11</name>
		<pose>Unspecified</pose>
		<truncated>0</truncated>
		<difficult>0</difficult>
		<bndbox>
			<xmin>450</xmin>
			<ymin>693</ymin>
			<xmax>566</xmax>
			<ymax>812</ymax>
		</bndbox>
	</object>
</annotation>