<annotation>
	<filename>733.xml</filename>
	<source>
		<database>MAR20</database>
	</source>
	<size>
		<width>758</width>
		<height>779</height>
		<depth>3</depth>
	</size>
	<segmented>0</segmented>
	<object>
		<name>A13</name>
		<bndbox>
			<xmin>88</xmin>
			<ymin>133</ymin>
			<xmax>132</xmax>
			<ymax>181</ymax>
		</bndbox>
	<difficult>0</difficult></object>
	<object>
		<name>A13</name>
		<bndbox>
			<xmin>173</xmin>
			<ymin>146</ymin>
			<xmax>217</xmax>
			<ymax>192</ymax>
		</bndbox>
	<difficult>0</difficult></object>
	<object>
		<name>A13</name>
		<bndbox>
			<xmin>420</xmin>
			<ymin>192</ymin>
			<xmax>470</xmax>
			<ymax>245</ymax>
		</bndbox>
	<difficult>0</difficult></object>
	<object>
		<name>A13</name>
		<bndbox>
			<xmin>508</xmin>
			<ymin>402</ymin>
			<xmax>567</xmax>
			<ymax>443</ymax>
		</bndbox>
	<difficult>0</difficult></object>
	<object>
		<name>A13</name>
		<bndbox>
			<xmin>492</xmin>
			<ymin>487</ymin>
			<xmax>550</xmax>
			<ymax>526</ymax>
		</bndbox>
	<difficult>0</difficult></object>
	<object>
		<name>A13</name>
		<bndbox>
			<xmin>478</xmin>
			<ymin>572</ymin>
			<xmax>535</xmax>
			<ymax>613</ymax>
		</bndbox>
	<difficult>0</difficult></object>
	<object>
		<name>A13</name>
		<bndbox>
			<xmin>462</xmin>
			<ymin>651</ymin>
			<xmax>523</xmax>
			<ymax>696</ymax>
		</bndbox>
	<difficult>0</difficult></object>
</annotation>