<annotation>
	<folder>Unknown</folder>
	<filename>928.jpg</filename>
	<path>Unknown</path>
	<source>
		<database>MAR20</database>
	</source>
	<size>
		<width>800</width>
		<height>800</height>
		<depth>3</depth>
	</size>
	<segmented>0</segmented>
	<object>
		<name>A19</name>
		<pose>Unspecified</pose>
		<truncated>0</truncated>
		<difficult>0</difficult>
		<bndbox>
			<xmin>226</xmin>
			<ymin>91</ymin>
			<xmax>339</xmax>
			<ymax>246</ymax>
		</bndbox>
	</object>
	<object>
		<name>A19</name>
		<pose>Unspecified</pose>
		<truncated>0</truncated>
		<difficult>0</difficult>
		<bndbox>
			<xmin>612</xmin>
			<ymin>266</ymin>
			<xmax>726</xmax>
			<ymax>416</ymax>
		</bndbox>
	</object>
	<object>
		<name>A19</name>
		<pose>Unspecified</pose>
		<truncated>0</truncated>
		<difficult>0</difficult>
		<bndbox>
			<xmin>224</xmin>
			<ymin>590</ymin>
			<xmax>340</xmax>
			<ymax>749</ymax>
		</bndbox>
	</object>
</annotation>